proxtorch/__init__.py
proxtorch/base.py
proxtorch/constraints/__init__.py
proxtorch/constraints/box.py
proxtorch/constraints/frobenius.py
proxtorch/constraints/l0ball.py
proxtorch/constraints/l1ball.py
proxtorch/constraints/l2ball.py
proxtorch/constraints/lInfinityBall.py
proxtorch/constraints/non_negative.py
proxtorch/constraints/rank.py
proxtorch/constraints/tracenorm.py
proxtorch/operators/__init__.py
proxtorch/operators/dummy.py
proxtorch/operators/elastic_net.py
proxtorch/operators/frobenius.py
proxtorch/operators/fused_lasso.py
proxtorch/operators/graphnet.py
proxtorch/operators/group_lasso.py
proxtorch/operators/huber.py
proxtorch/operators/l1.py
proxtorch/operators/l2.py
proxtorch/operators/tracenorm.py
proxtorch/operators/tv_2d.py
proxtorch/operators/tv_3d.py
proxtorch/operators/tvl1_2d.py
proxtorch/operators/tvl1_3d.py
proxtorch-0.0.9.dist-info/LICENSE
proxtorch-0.0.9.dist-info/METADATA
proxtorch-0.0.9.dist-info/WHEEL
proxtorch-0.0.9.dist-info/RECORD
