Metadata-Version: 2.1
Name: ProxTorch
Version: 0.0.9
Summary: ProxTorch is a PyTorch library for proximal operators.
Home-page: https://github.com/jameschapman19/proxtorch
License: MIT
Keywords: proximal,optimisation,pytorch,proximal operators
Author: jameschapman
Author-email: james.chapman.19@ucl.ac.uk
Requires-Python: >=3.8,<4.0.0
Classifier: License :: OSI Approved :: MIT License
Classifier: Programming Language :: Python :: 3
Classifier: Programming Language :: Python :: 3.8
Classifier: Programming Language :: Python :: 3.9
Classifier: Programming Language :: Python :: 3.10
Classifier: Programming Language :: Python :: 3.11
Requires-Dist: torch (>=2.0.1,<3.0.0) ; sys_platform == "darwin"
Requires-Dist: torch (>=2.0.1,<3.0.0) ; sys_platform == "linux"
Requires-Dist: torch (>=2.0.1,<3.0.0) ; sys_platform == "win32"
